drivel/__init__.py
drivel/constants.py
drivel/exceptions.py
drivel/themes.py
drivel/utilities.py
drivel/assets/alice.yaml
drivel/assets/batman.yaml
drivel/assets/bible.yaml
drivel/assets/care-bears.yaml
drivel/assets/constellations.yaml
drivel/assets/crypto.yaml
drivel/assets/debian.yaml
drivel/assets/drivel.yaml
drivel/assets/foobar.yaml
drivel/assets/jabberwocky.yaml
drivel/assets/octothorpe.yaml
drivel/assets/python.yaml
drivel/assets/smurfs.yaml
drivel/assets/star-wars.yaml
drivel/assets/stars.yaml
drivel/assets/swords.yaml
drivel/assets/tarot.yaml
drivel/assets/ubuntu.yaml
drivel/assets/zodiac.yaml
drivel/cli/__init__.py
drivel/cli/cache.py
drivel/cli/config.py
drivel/cli/constants.py
drivel/cli/exceptions.py
drivel/cli/extra_themes.py
drivel/cli/format.py
drivel/cli/give.py
drivel/cli/logging.py
drivel/cli/main.py
drivel/cli/schemas.py
drivel/cli/share.py
drivel/cli/themes.py
drivel/cli/utilities.py
drivel/cli/version.py
py_drivel-0.2.0.dist-info/METADATA
py_drivel-0.2.0.dist-info/WHEEL
py_drivel-0.2.0.dist-info/entry_points.txt
py_drivel-0.2.0.dist-info/licenses/LICENSE.md
py_drivel-0.2.0.dist-info/RECORD
