Metadata-Version: 2.4
Name: py-drivel
Version: 0.2.0
Summary: Get fun metasyntactic variable names
Project-URL: homepage, https://github.com/dusktreader/drivel
Project-URL: source, https://github.com/dusktreader/drivel
Project-URL: changelog, https://github.com/dusktreader/drivel/blob/main/CHANGELOG.md
Author-email: Tucker Beck <tucker.beck@gmail.com>
License-File: LICENSE.md
Requires-Python: >=3.10
Requires-Dist: auto-name-enum>=2.0.0
Requires-Dist: inflection>=0.5.1
Requires-Dist: loguru>=0.7.3
Requires-Dist: py-buzz~=6.0.3
Requires-Dist: pydantic>=2.10.6
Requires-Dist: pyperclip>=1.9.0
Requires-Dist: pyyaml>=6.0.2
Requires-Dist: snick>=1.4.1
Requires-Dist: toml>=0.10.2
Requires-Dist: typer>=0.15.2
